beautifulplots/__init__.py
beautifulplots/barplot.py
beautifulplots/beautifulplots.py
beautifulplots/lineplot.py
beautifulplots/scatterplot.py
beautifulplots-0.2.8.dist-info/LICENSE
beautifulplots-0.2.8.dist-info/WHEEL
beautifulplots-0.2.8.dist-info/METADATA
beautifulplots-0.2.8.dist-info/RECORD
