Metadata-Version: 2.1
Name: beautifulplots
Version: 0.2.8
Summary: Python plotting library for beautiful, easy, and sophisticated matplotlib based plots. Compatible with Pandas and Seaborn plots.
License: MIT
Author: Alberto Gutierrez
Requires-Python: >=3.9
Classifier: License :: OSI Approved :: MIT License
Classifier: Programming Language :: Python :: 3
Classifier: Programming Language :: Python :: 3.10
Classifier: Programming Language :: Python :: 3.9
Requires-Dist: matplotlib (>=3.4)
Requires-Dist: pandas (>=1.0)
Requires-Dist: seaborn (>=0.13.2)
